revenium_metering/__init__.py
revenium_metering/_base_client.py
revenium_metering/_client.py
revenium_metering/_compat.py
revenium_metering/_constants.py
revenium_metering/_exceptions.py
revenium_metering/_files.py
revenium_metering/_models.py
revenium_metering/_qs.py
revenium_metering/_resource.py
revenium_metering/_response.py
revenium_metering/_streaming.py
revenium_metering/_types.py
revenium_metering/_version.py
revenium_metering/context.py
revenium_metering/decorator.py
revenium_metering/py.typed
revenium_metering/_utils/__init__.py
revenium_metering/_utils/_logs.py
revenium_metering/_utils/_proxy.py
revenium_metering/_utils/_reflection.py
revenium_metering/_utils/_resources_proxy.py
revenium_metering/_utils/_streams.py
revenium_metering/_utils/_sync.py
revenium_metering/_utils/_transform.py
revenium_metering/_utils/_typing.py
revenium_metering/_utils/_utils.py
revenium_metering/lib/.keep
revenium_metering/resources/__init__.py
revenium_metering/resources/ai.py
revenium_metering/resources/apis.py
revenium_metering/resources/events.py
revenium_metering/types/__init__.py
revenium_metering/types/ai_create_audio_params.py
revenium_metering/types/ai_create_completion_params.py
revenium_metering/types/ai_create_image_params.py
revenium_metering/types/ai_create_video_params.py
revenium_metering/types/api_meter_request_params.py
revenium_metering/types/api_meter_response_params.py
revenium_metering/types/event_create_params.py
revenium_metering/types/metering_response_resource.py
revenium_metering-6.8.0.dist-info/METADATA
revenium_metering-6.8.0.dist-info/WHEEL
revenium_metering-6.8.0.dist-info/licenses/LICENSE
revenium_metering-6.8.0.dist-info/RECORD
